{
	"_version": "1.1.0",
	"resources": [
		{
			"name": "AnnotationHelper-dbg.js",
			"size": 17669,
			"isDebug": true
		},
		{
			"name": "AnnotationHelper.js",
			"size": 7878
		},
		{
			"name": "Component-dbg.js",
			"size": 3997,
			"isDebug": true
		},
		{
			"name": "Component.js",
			"size": 1774
		},
		{
			"name": "ObjectPage.view.xml",
			"size": 6846
		},
		{
			"name": "ObjectPageController-dbg.controller.js",
			"size": 32532,
			"isDebug": true
		},
		{
			"name": "ObjectPageController.controller.js",
			"size": 13852
		},
		{
			"name": "controls/SubSectionBlock-dbg.js",
			"size": 1594,
			"isDebug": true
		},
		{
			"name": "controls/SubSectionBlock.js",
			"size": 924
		},
		{
			"name": "macros/SubSectionBlockContent.fragment.xml",
			"size": 335
		},
		{
			"name": "macros/SubSectionBlockContent.metadata-dbg.js",
			"size": 2153,
			"isDebug": true
		},
		{
			"name": "macros/SubSectionBlockContent.metadata.js",
			"size": 767
		},
		{
			"name": "macros/macroLibrary-dbg.js",
			"size": 2535,
			"isDebug": true
		},
		{
			"name": "macros/macroLibrary.js",
			"size": 616
		},
		{
			"name": "manifest.json",
			"size": 2226
		},
		{
			"name": "view/fragments/Actions.fragment.xml",
			"size": 4775
		},
		{
			"name": "view/fragments/EditableHeaderContact.fragment.xml",
			"size": 775
		},
		{
			"name": "view/fragments/EditableHeaderFacet.fragment.xml",
			"size": 2857
		},
		{
			"name": "view/fragments/Facet.fragment.xml",
			"size": 1466
		},
		{
			"name": "view/fragments/FooterContent.fragment.xml",
			"size": 4150
		},
		{
			"name": "view/fragments/FormActionButtons.fragment.xml",
			"size": 537
		},
		{
			"name": "view/fragments/FormActions.fragment.xml",
			"size": 734
		},
		{
			"name": "view/fragments/HeaderContent.fragment.xml",
			"size": 1423
		},
		{
			"name": "view/fragments/HeaderDataPoint.fragment.xml",
			"size": 931
		},
		{
			"name": "view/fragments/HeaderDataPointContent.fragment.xml",
			"size": 1649
		},
		{
			"name": "view/fragments/HeaderExpandedAndSnappedContent.fragment.xml",
			"size": 488
		},
		{
			"name": "view/fragments/HeaderFacet.fragment.xml",
			"size": 4275
		},
		{
			"name": "view/fragments/HeaderImage.fragment.xml",
			"size": 787
		},
		{
			"name": "view/fragments/HeaderProgressIndicator.fragment.xml",
			"size": 1979
		},
		{
			"name": "view/fragments/HeaderRatingIndicator.fragment.xml",
			"size": 1919
		},
		{
			"name": "view/fragments/ObjectPageForm.fragment.xml",
			"size": 951
		},
		{
			"name": "view/fragments/ObjectPageHeaderForm.fragment.xml",
			"size": 3078
		},
		{
			"name": "view/fragments/RelatedApps.fragment.xml",
			"size": 683
		},
		{
			"name": "view/fragments/Section.fragment.xml",
			"size": 4040
		},
		{
			"name": "view/fragments/TitleAndSubtitle.fragment.xml",
			"size": 759
		}
	]
}